dark_send/__init__.py
dark_send/cli.py
dark_send/config.py
dark_send/core.py
dark_send/daemon.py
dark_send/inquirer.py
dark_send/meta_data.py
dark_send/progress_bar.py
dark_send-1.2.0.dist-info/licenses/LICENSE
dark_send-1.2.0.dist-info/METADATA
dark_send-1.2.0.dist-info/WHEEL
dark_send-1.2.0.dist-info/entry_points.txt
dark_send-1.2.0.dist-info/top_level.txt
dark_send-1.2.0.dist-info/RECORD
