Metadata-Version: 2.4
Name: dark-send
Version: 1.2.0
Summary: A Command Line Interface for Telegram
Home-page: https://github.com/mindhuntr/dark-send
Author: Irfan Jalal
Author-email: mindhunter@blinkenshell.org
Classifier: Programming Language :: Python :: 3
Classifier: License :: OSI Approved :: MIT License
Classifier: Operating System :: OS Independent
Requires-Python: >=3.8
License-File: LICENSE
Requires-Dist: hachoir>=3.3.0
Requires-Dist: InquirerPy>=0.3.4
Requires-Dist: telethon>=1.37.0
Requires-Dist: tqdm>=4.60.0
Dynamic: author
Dynamic: author-email
Dynamic: classifier
Dynamic: description
Dynamic: description-content-type
Dynamic: home-page
Dynamic: license-file
Dynamic: requires-dist
Dynamic: requires-python
Dynamic: summary
